{
    "resultValue": [
        {
             "title":"芜湖站",
             "id":10
        },
        {
             "title":"合肥站",
             "id":11
        },
        {
             "title":"南京分拨中心",
             "id":12
        },
        {
             "title":"无锡站",
             "id":13
        },
        {
             "title":"南通站",
             "id":14
        },
        {
             "title":"盐城站",
             "id":15
        },
        {
             "title":"连云港站",
             "id":16
        },
        {
             "title":"大连站",
             "id":16
        },
        {
             "title":"深圳站",
             "id":16
        },
        {
             "title":"安徽站",
             "id":16
        }
        
    ]
}